runup/yaml_parser.cpython-39-x86_64-linux-gnu.so
runup/db.cpython-39-x86_64-linux-gnu.so
runup/__init__.cpython-39-x86_64-linux-gnu.so
runup/__init__.py
runup/cli.cpython-39-x86_64-linux-gnu.so
runup/version.cpython-39-x86_64-linux-gnu.so
runup/config.cpython-39-x86_64-linux-gnu.so
runup/interpreter.cpython-39-x86_64-linux-gnu.so
runup/utils.cpython-39-x86_64-linux-gnu.so
RunUp-0.1b4.dist-info/LICENSE
RunUp-0.1b4.dist-info/METADATA
RunUp-0.1b4.dist-info/top_level.txt
RunUp-0.1b4.dist-info/RECORD
RunUp-0.1b4.dist-info/WHEEL
RunUp-0.1b4.dist-info/entry_points.txt
