Metadata-Version: 2.1
Name: RunUp
Version: 0.1b4
Summary: RunUp is a backup system that can be managed by command line.
Home-page: UNKNOWN
Author: Kenny Lajara
Author-email: kennylajara@gmail.com
License: UNKNOWN
Project-URL: Documentation, https://runup.readthedocs.io/
Project-URL: Tracker, https://github.com/kennylajara/runup/issues
Project-URL: Source, https://github.com/kennylajara/runup
Platform: UNKNOWN
Classifier: Development Status :: 4 - Beta
Classifier: Environment :: Console
Classifier: Intended Audience :: Developers
Classifier: Intended Audience :: Information Technology
Classifier: Intended Audience :: System Administrators
Classifier: License :: OSI Approved :: Mozilla Public License 1.0 (MPL)
Classifier: Operating System :: POSIX :: Linux
Classifier: Operating System :: MacOS
Classifier: Operating System :: Microsoft :: Windows
Classifier: Programming Language :: Cython
Classifier: Programming Language :: Python
Classifier: Programming Language :: Python :: 3
Classifier: Programming Language :: Python :: 3.7
Classifier: Programming Language :: Python :: 3.8
Classifier: Programming Language :: Python :: 3.9
Classifier: Topic :: System :: Archiving :: Backup
Classifier: Topic :: System :: Archiving :: Compression
Classifier: Topic :: System :: Recovery Tools
Requires-Python: >=3.6
Requires-Dist: Click (==8.0.1)
Requires-Dist: pyyaml (==5.4.1)
